MANIFEST.in
README.md
setup.py
api/__init__.py
api/context.py
api/hashing.py
api/login.py
api/main.py
api/models.py
api/oauth2.py
api/schemas.py
api/show.py
api/routers/__init__.py
api/routers/authentication.py
api/routers/case.py
api/routers/prwebform.py
api/routers/user.py
basemodels/__init__.py
basemodels/address.py
basemodels/advertisement.py
basemodels/commonmodel.py
basemodels/contact.py
basemodels/context.py
basemodels/cor.py
basemodels/educationbase.py
basemodels/employerbase.py
basemodels/employmentbase.py
basemodels/employmenthistory.py
basemodels/errordict.py
basemodels/family.py
basemodels/finance.py
basemodels/formmodel.py
basemodels/id.py
basemodels/jobofferbase.py
basemodels/jobposition.py
basemodels/language.py
basemodels/m5476.py
basemodels/mediaaccount.py
basemodels/mixins.py
basemodels/modelloader.py
basemodels/person.py
basemodels/phone.py
basemodels/rcic.py
basemodels/status.py
basemodels/tr.py
basemodels/trperson.py
basemodels/user.py
basemodels/utils.py
basemodels/wordmaker.py
basemodels/xmlfiller.py
basemodels/xmlmaker.py
basemodels/data/__init__.py
basemodels/data/city.py
basemodels/data/country.py
basemodels/data/language.py
basemodels/data/other.py
basemodels/experience/__init__.py
basemodels/experience/context.py
basemodels/experience/data.py
basemodels/experience/employmentcert.py
basemodels/experience/experience.py
basemodels/experience/resume.py
basemodels/experience/resumedata.py
basemodels/pdfform/__init__.py
basemodels/pdfform/application_form.py
basemodels/pdfform/config_mac.py
basemodels/pdfform/config_win.py
basemodels/pdfform/context.py
basemodels/pdfform/fb5476.py
basemodels/pdfform/form_controls_mac.py
basemodels/pdfform/form_controls_win.py
basemodels/pdfform/jsonmaker.py
basemodels/recruit/__init__.py
basemodels/recruit/context.py
basemodels/recruit/jobad.py
basemodels/recruit/jobaddata.py
basemodels/recruit/joboffer.py
basemodels/recruit/jobofferdata.py
basemodels/recruit/recruitmentsummary.py
imm_apps.egg-info/PKG-INFO
imm_apps.egg-info/SOURCES.txt
imm_apps.egg-info/dependency_links.txt
imm_apps.egg-info/entry_points.txt
imm_apps.egg-info/top_level.txt
